Workbook

Sheet Cómo usar
B1: Plantilla de costos, precio y punto de equilibrio (A8)
B2: Ruta HACER · Semana 4 · Centro de Innovación Comunitario · Red de Mujeres del Caribe
B4: Para qué sirve
B5: Para saber cuánto te cuesta hacer cada producto, si tu precio te deja ganancia o te hace perder, qué precio te conviene (con piso y techo) y cuánto tienes que vender para no perder (punto de equilibrio). Es un apoyo opcional: todo se puede hacer en papel con la plantilla impresa A8.
B7: Cómo se usa
B8: 1. Hoja «Costeo por producto», tabla de arriba: escribe el nombre de cada producto (hasta 8), su precio de hoy, el precio del mercado (techo) y, cuando lo decidas, tu nuevo precio. En la celda amarilla de arriba escribe la ganancia que deseas sobre el costo (por ejemplo 30 %).
B9: 2. Misma hoja, tabla de abajo («Detalle de costos»): una fila por cada cosa que lleva el producto. Escoge el producto y el tipo de costo (Materia prima, Mano de obra o Costo indirecto). Escribe lo que pagaste y para cuántas unidades te alcanza: la hoja calcula el costo por unidad.
B10: 3. No olvides tu propio trabajo: en «Mano de obra» escribe lo que te pagarías por un día (o por una tanda) y cuántas unidades haces en ese tiempo.
B11: 4. La tabla de arriba se llena sola: costo por unidad, margen, alerta «¡Pierdes plata!», precio sugerido y si tu nuevo precio queda entre el piso y el techo.
B12: 5. Hoja «Punto de equilibrio»: escribe los gastos que pagas vendas o no vendas (al mes), los días que vendes al mes y a la semana, y cuántas unidades vendes al día de cada producto. La hoja calcula el margen promedio y el punto de equilibrio por mes, semana y día.
B14: Importante
B15: Las filas con fondo crema y letra gris son un EJEMPLO (Marta, jugos naturales; caso ilustrativo). Bórralas o escribe encima antes de usar la hoja con tus datos.
... B20: Celda amarilla = la llenas tú. Celda blanca = se calcula sola, no la borres.

Sheet Costeo por producto
A1: Costeo por producto
A2: Ganancia que deseas sobre el costo (para el precio sugerido): | F2: 0.3 | G2: ← por ejemplo 30 %
A4: Producto | B4: Materia prima por unidad | C4: Mano de obra por unidad | D4: Costos indirectos por unidad | E4: Costo por unidad (piso) | F4: Precio de hoy | G4: Margen de hoy | H4: Alerta | I4: Precio sugerido | J4: Techo (precio del mercado) | K4: Nuevo precio (tu decisión) | L4: Nuevo margen | M4: ¿Nuevo precio entre piso y techo?
A5: Vaso pequeño | B5: =IF($A5="","",SUMIFS($F$17:$F$116,$A$17:$A$116,$A5,$B$17:$B$116,"Materia prima")) -> 1000 | C5: =IF($A5="","",SUMIFS($F$17:$F$116,$A$17:$A$116,$A5,$B$17:$B$116,"Mano de obra")) -> 400 | D5: =IF($A5="","",SUMIFS($F$17:$F$116,$A$17:$A$116,$A5,$B$17:$B$116,"Costo indirecto")) -> 150 | E5: =IF($A5="","",B5+C5+D5) -> 1550 | F5: 2000 | G5: =IF(OR($A5="",F5=""),"",F5-E5) -> 450 | H5: =IF(G5="","",IF(G5<0,"¡Pierdes plata!",IF(G5=0,"No ganas nada","Te deja ganancia"))) -> Te deja ganancia | I5: =IF($A5="","",ROUND(E5*(1+$F$2),-2)) -> 2000 | K5: 2000 | L5: =IF(OR($A5="",K5=""),"",K5-E5) -> 450 | M5: =IF(OR($A5="",K5=""),"",IF(K5<E5,"Por debajo del piso: pierdes",IF(J5="","Encima del piso (sin techo)",IF(K5>J5,"Por encima del techo","Sí, entre piso y techo")))) -> Encima del piso (sin techo)
A6: Vaso grande | B6: =IF($A6="","",SUMIFS($F$17:$F$116,$A$17:$A$116,$A6,$B$17:$B$116,"Materia prima")) -> 2150 | C6: =IF($A6="","",SUMIFS($F$17:$F$116,$A$17:$A$116,$A6,$B$17:$B$116,"Mano de obra")) -> 700 | D6: =IF($A6="","",SUMIFS($F$17:$F$116,$A$17:$A$116,$A6,$B$17:$B$116,"Costo indirecto")) -> 250 | E6: =IF($A6="","",B6+C6+D6) -> 3100 | F6: 3000 | G6: =IF(OR($A6="",F6=""),"",F6-E6) -> -100 | H6: =IF(G6="","",IF(G6<0,"¡Pierdes plata!",IF(G6=0,"No ganas nada","Te deja ganancia"))) -> ¡Pierdes plata! | I6: =IF($A6="","",ROUND(E6*(1+$F$2),-2)) -> 4000 | J6: 4500 | K6: 4000 | L6: =IF(OR($A6="",K6=""),"",K6-E6) -> 900 | M6: =IF(OR($A6="",K6=""),"",IF(K6<E6,"Por debajo del piso: pierdes",IF(J6="","Encima del piso (sin techo)",IF(K6>J6,"Por encima del techo","Sí, entre piso y techo")))) -> Sí, entre piso y techo
B7: =IF($A7="","",SUMIFS($F$17:$F$116,$A$17:$A$116,$A7,$B$17:$B$116,"Materia prima")) | C7: =IF($A7="","",SUMIFS($F$17:$F$116,$A$17:$A$116,$A7,$B$17:$B$116,"Mano de obra")) | D7: =IF($A7="","",SUMIFS($F$17:$F$116,$A$17:$A$116,$A7,$B$17:$B$116,"Costo indirecto")) | E7: =IF($A7="","",B7+C7+D7) | G7: =IF(OR($A7="",F7=""),"",F7-E7) | H7: =IF(G7="","",IF(G7<0,"¡Pierdes plata!",IF(G7=0,"No ganas nada","Te deja ganancia"))) | I7: =IF($A7="","",ROUND(E7*(1+$F$2),-2)) | L7: =IF(OR($A7="",K7=""),"",K7-E7) | M7: =IF(OR($A7="",K7=""),"",IF(K7<E7,"Por debajo del piso: pierdes",IF(J7="","Encima del piso (sin techo)",IF(K7>J7,"Por encima del techo","Sí, entre piso y techo"))))
B8: =IF($A8="","",SUMIFS($F$17:$F$116,$A$17:$A$116,$A8,$B$17:$B$116,"Materia prima")) | C8: =IF($A8="","",SUMIFS($F$17:$F$116,$A$17:$A$116,$A8,$B$17:$B$116,"Mano de obra")) | D8: =IF($A8="","",SUMIFS($F$17:$F$116,$A$17:$A$116,$A8,$B$17:$B$116,"Costo indirecto")) | E8: =IF($A8="","",B8+C8+D8) | G8: =IF(OR($A8="",F8=""),"",F8-E8) | H8: =IF(G8="","",IF(G8<0,"¡Pierdes plata!",IF(G8=0,"No ganas nada","Te deja ganancia"))) | I8: =IF($A8="","",ROUND(E8*(1+$F$2),-2)) | L8: =IF(OR($A8="",K8=""),"",K8-E8) | M8: =IF(OR($A8="",K8=""),"",IF(K8<E8,"Por debajo del piso: pierdes",IF(J8="","Encima del piso (sin techo)",IF(K8>J8,"Por encima del techo","Sí, entre piso y techo"))))
B9: =IF($A9="","",SUMIFS($F$17:$F$116,$A$17:$A$116,$A9,$B$17:$B$116,"Materia prima")) | C9: =IF($A9="","",SUMIFS($F$17:$F$116,$A$17:$A$116,$A9,$B$17:$B$116,"Mano de obra")) | D9: =IF($A9="","",SUMIFS($F$17:$F$116,$A$17:$A$116,$A9,$B$17:$B$116,"Costo indirecto")) | E9: =IF($A9="","",B9+C9+D9) | G9: =IF(OR($A9="",F9=""),"",F9-E9) | H9: =IF(G9="","",IF(G9<0,"¡Pierdes plata!",IF(G9=0,"No ganas nada","Te deja ganancia"))) | I9: =IF($A9="","",ROUND(E9*(1+$F$2),-2)) | L9: =IF(OR($A9="",K9=""),"",K9-E9) | M9: =IF(OR($A9="",K9=""),"",IF(K9<E9,"Por debajo del piso: pierdes",IF(J9="","Encima del piso (sin techo)",IF(K9>J9,"Por encima del techo","Sí, entre piso y techo"))))
B10: =IF($A10="","",SUMIFS($F$17:$F$116,$A$17:$A$116,$A10,$B$17:$B$116,"Materia prima")) | C10: =IF($A10="","",SUMIFS($F$17:$F$116,$A$17:$A$116,$A10,$B$17:$B$116,"Mano de obra")) | D10: =IF($A10="","",SUMIFS($F$17:$F$116,$A$17:$A$116,$A10,$B$17:$B$116,"Costo indirecto")) | E10: =IF($A10="","",B10+C10+D10) | G10: =IF(OR($A10="",F10=""),"",F10-E10) | H10: =IF(G10="","",IF(G10<0,"¡Pierdes plata!",IF(G10=0,"No ganas nada","Te deja ganancia"))) | I10: =IF($A10="","",ROUND(E10*(1+$F$2),-2)) | L10: =IF(OR($A10="",K10=""),"",K10-E10) | M10: =IF(OR($A10="",K10=""),"",IF(K10<E10,"Por debajo del piso: pierdes",IF(J10="","Encima del piso (sin techo)",IF(K10>J10,"Por encima del techo","Sí, entre piso y techo"))))
B11: =IF($A11="","",SUMIFS($F$17:$F$116,$A$17:$A$116,$A11,$B$17:$B$116,"Materia prima")) | C11: =IF($A11="","",SUMIFS($F$17:$F$116,$A$17:$A$116,$A11,$B$17:$B$116,"Mano de obra")) | D11: =IF($A11="","",SUMIFS($F$17:$F$116,$A$17:$A$116,$A11,$B$17:$B$116,"Costo indirecto")) | E11: =IF($A11="","",B11+C11+D11) | G11: =IF(OR($A11="",F11=""),"",F11-E11) | H11: =IF(G11="","",IF(G11<0,"¡Pierdes plata!",IF(G11=0,"No ganas nada","Te deja ganancia"))) | I11: =IF($A11="","",ROUND(E11*(1+$F$2),-2)) | L11: =IF(OR($A11="",K11=""),"",K11-E11) | M11: =IF(OR($A11="",K11=""),"",IF(K11<E11,"Por debajo del piso: pierdes",IF(J11="","Encima del piso (sin techo)",IF(K11>J11,"Por encima del techo","Sí, entre piso y techo"))))
B12: =IF($A12="","",SUMIFS($F$17:$F$116,$A$17:$A$116,$A12,$B$17:$B$116,"Materia prima")) | C12: =IF($A12="","",SUMIFS($F$17:$F$116,$A$17:$A$116,$A12,$B$17:$B$116,"Mano de obra")) | D12: =IF($A12="","",SUMIFS($F$17:$F$116,$A$17:$A$116,$A12,$B$17:$B$116,"Costo indirecto")) | E12: =IF($A12="","",B12+C12+D12) | G12: =IF(OR($A12="",F12=""),"",F12-E12) | H12: =IF(G12="","",IF(G12<0,"¡Pierdes plata!",IF(G12=0,"No ganas nada","Te deja ganancia"))) | I12: =IF($A12="","",ROUND(E12*(1+$F$2),-2)) | L12: =IF(OR($A12="",K12=""),"",K12-E12) | M12: =IF(OR($A12="",K12=""),"",IF(K12<E12,"Por debajo del piso: pierdes",IF(J12="","Encima del piso (sin techo)",IF(K12>J12,"Por encima del techo","Sí, entre piso y techo"))))
A13: Precio sugerido = costo × (1 + ganancia deseada), redondeado a la centena. Es solo una referencia: tú decides el nuevo precio mirando el piso (costo), el mercado y el valor que aprecian tus clientes.
A15: Detalle de costos (una fila por cada cosa que lleva el producto) | H15: Las filas crema son el ejemplo de Marta: bórralas o escribe encima.
A16: Producto (escoge) | B16: Tipo de costo | C16: Concepto | D16: Lo que pagué ($) | E16: ¿Para cuántas unidades alcanza? | F16: Costo por unidad
A17: Vaso pequeño | B17: Materia prima | C17: Fruta para 32 vasos | D17: 22400 | E17: 32 | F17: =IF(OR(D17="",E17="",E17=0),"",D17/E17) -> 700
A18: Vaso pequeño | B18: Materia prima | C18: Azúcar para 32 vasos | D18: 2560 | E18: 32 | F18: =IF(OR(D18="",E18="",E18=0),"",D18/E18) -> 80
A19: Vaso pequeño | B19: Materia prima | C19: Hielo para 32 vasos | D19: 2880 | E19: 32 | F19: =IF(OR(D19="",E19="",E19=0),"",D19/E19) -> 90
A20: Vaso pequeño | B20: Materia prima | C20: Vasos y pitillos (32) | D20: 4160 | E20: 32 | F20: =IF(OR(D20="",E20="",E20=0),"",D20/E20) -> 130
A21: Vaso pequeño | B21: Mano de obra | C21: Mi pago por los 32 vasos pequeños del día | D21: 12800 | E21: 32 | F21: =IF(OR(D21="",E21="",E21=0),"",D21/E21) -> 400
A22: Vaso pequeño | B22: Costo indirecto | C22: Energía, agua y transporte (parte de los 32 vasos) | D22: 4800 | E22: 32 | F22: =IF(OR(D22="",E22="",E22=0),"",D22/E22) -> 150
A23: Vaso grande | B23: Materia prima | C23: Fruta para 8 vasos | D23: 12800 | E23: 8 | F23: =IF(OR(D23="",E23="",E23=0),"",D23/E23) -> 1600
A24: Vaso grande | B24: Materia prima | C24: Azúcar para 8 vasos | D24: 1200 | E24: 8 | F24: =IF(OR(D24="",E24="",E24=0),"",D24/E24) -> 150
A25: Vaso grande | B25: Materia prima | C25: Hielo para 8 vasos | D25: 1200 | E25: 8 | F25: =IF(OR(D25="",E25="",E25=0),"",D25/E25) -> 150
A26: Vaso grande | B26: Materia prima | C26: Vasos con tapa y pitillos (8) | D26: 2000 | E26: 8 | F26: =IF(OR(D26="",E26="",E26=0),"",D26/E26) -> 250
A27: Vaso grande | B27: Mano de obra | C27: Mi pago por los 8 vasos grandes del día | D27: 5600 | E27: 8 | F27: =IF(OR(D27="",E27="",E27=0),"",D27/E27) -> 700
A28: Vaso grande | B28: Costo indirecto | C28: Energía, agua y transporte (parte de los 8 vasos) | D28: 2000 | E28: 8 | F28: =IF(OR(D28="",E28="",E28=0),"",D28/E28) -> 250
F29: =IF(OR(D29="",E29="",E29=0),"",D29/E29)
F30: =IF(OR(D30="",E30="",E30=0),"",D30/E30)
F31: =IF(OR(D31="",E31="",E31=0),"",D31/E31)
F32: =IF(OR(D32="",E32="",E32=0),"",D32/E32)
F33: =IF(OR(D33="",E33="",E33=0),"",D33/E33)
F34: =IF(OR(D34="",E34="",E34=0),"",D34/E34)
F35: =IF(OR(D35="",E35="",E35=0),"",D35/E35)
F36: =IF(OR(D36="",E36="",E36=0),"",D36/E36)
F37: =IF(OR(D37="",E37="",E37=0),"",D37/E37)
F38: =IF(OR(D38="",E38="",E38=0),"",D38/E38)
F39: =IF(OR(D39="",E39="",E39=0),"",D39/E39)
F40: =IF(OR(D40="",E40="",E40=0),"",D40/E40)
... F116: =IF(OR(D116="",E116="",E116=0),"",D116/E116)

Sheet Punto de equilibrio
A1: Mi punto de equilibrio
A2: Lo que tengo que vender para no perder: gastos que pago vendas o no vendas ÷ margen promedio por unidad.
A4: 1. Gastos que pago vendas o no vendas (al mes)
A5: Gasto | B5: Valor al mes
A6: Bodegaje del carrito | B6: 80000
A7: Recarga del celular | B7: 30000
A8: Mantenimiento de licuadora y carrito | B8: 40000
A9: Aporte por el uso del espacio | B9: 30000
A14: Total de gastos del mes (G) | B14: =SUM(B6:B13) -> 180000
A16: 2. ¿Cada cuánto vendo?
A17: Días que vendo al mes | B17: 20
A18: Días que vendo a la semana | B18: 5
A19: Semanas de venta al mes | B19: =IF(B18=0,0,B17/B18) -> 4
A21: 3. Lo que vendo de cada producto (la hoja trae el nuevo margen de «Costeo por producto»)
A22: Producto | B22: Unidades que vendo al día | C22: Precio que uso | D22: Margen por unidad | E22: Unidades × margen
A23: =IF('Costeo por producto'!A5="","",'Costeo por producto'!A5) -> Vaso pequeño | B23: 32 | C23: =IF(A23="","",IF('Costeo por producto'!K5="",'Costeo por producto'!F5,'Costeo por producto'!K5)) -> 2000 | D23: =IF(OR(A23="",C23=""),"",C23-'Costeo por producto'!E5) -> 450 | E23: =IF(OR(B23="",D23=""),0,B23*D23) -> 14400
A24: =IF('Costeo por producto'!A6="","",'Costeo por producto'!A6) -> Vaso grande | B24: 8 | C24: =IF(A24="","",IF('Costeo por producto'!K6="",'Costeo por producto'!F6,'Costeo por producto'!K6)) -> 4000 | D24: =IF(OR(A24="",C24=""),"",C24-'Costeo por producto'!E6) -> 900 | E24: =IF(OR(B24="",D24=""),0,B24*D24) -> 7200
A25: =IF('Costeo por producto'!A7="","",'Costeo por producto'!A7) | C25: =IF(A25="","",IF('Costeo por producto'!K7="",'Costeo por producto'!F7,'Costeo por producto'!K7)) | D25: =IF(OR(A25="",C25=""),"",C25-'Costeo por producto'!E7) | E25: =IF(OR(B25="",D25=""),0,B25*D25) -> 0
A26: =IF('Costeo por producto'!A8="","",'Costeo por producto'!A8) | C26: =IF(A26="","",IF('Costeo por producto'!K8="",'Costeo por producto'!F8,'Costeo por producto'!K8)) | D26: =IF(OR(A26="",C26=""),"",C26-'Costeo por producto'!E8) | E26: =IF(OR(B26="",D26=""),0,B26*D26) -> 0
A27: =IF('Costeo por producto'!A9="","",'Costeo por producto'!A9) | C27: =IF(A27="","",IF('Costeo por producto'!K9="",'Costeo por producto'!F9,'Costeo por producto'!K9)) | D27: =IF(OR(A27="",C27=""),"",C27-'Costeo por producto'!E9) | E27: =IF(OR(B27="",D27=""),0,B27*D27) -> 0
A28: =IF('Costeo por producto'!A10="","",'Costeo por producto'!A10) | C28: =IF(A28="","",IF('Costeo por producto'!K10="",'Costeo por producto'!F10,'Costeo por producto'!K10)) | D28: =IF(OR(A28="",C28=""),"",C28-'Costeo por producto'!E10) | E28: =IF(OR(B28="",D28=""),0,B28*D28) -> 0
A29: =IF('Costeo por producto'!A11="","",'Costeo por producto'!A11) | C29: =IF(A29="","",IF('Costeo por producto'!K11="",'Costeo por producto'!F11,'Costeo por producto'!K11)) | D29: =IF(OR(A29="",C29=""),"",C29-'Costeo por producto'!E11) | E29: =IF(OR(B29="",D29=""),0,B29*D29) -> 0
A30: =IF('Costeo por producto'!A12="","",'Costeo por producto'!A12) | C30: =IF(A30="","",IF('Costeo por producto'!K12="",'Costeo por producto'!F12,'Costeo por producto'!K12)) | D30: =IF(OR(A30="",C30=""),"",C30-'Costeo por producto'!E12) | E30: =IF(OR(B30="",D30=""),0,B30*D30) -> 0
A31: Total | B31: =SUM(B23:B30) -> 40 | C31: =IF(B31=0,0,SUMPRODUCT(B23:B30,C23:C30)/B31) -> 2400 | E31: =SUM(E23:E30) -> 21600 | G31: ← en C31: precio promedio por unidad
A33: 4. Resultado
A34: Margen promedio por unidad (M = total unidades × margen ÷ total unidades) | B34: =IF(B31=0,0,E31/B31) -> 540
A35: Punto de equilibrio exacto al mes (G ÷ M) | B35: =IF(B34<=0,0,B14/B34) -> 333.33333
A36: Punto de equilibrio AL MES (unidades, redondeado hacia arriba) | B36: =ROUNDUP(B35,0) -> 334
A37: Punto de equilibrio A LA SEMANA (unidades) | B37: =IF(B19=0,0,ROUNDUP(B35/B19,0)) -> 84
A38: Punto de equilibrio AL DÍA (unidades) | B38: =IF(B17=0,0,ROUNDUP(B35/B17,0)) -> 17
A39: Punto de equilibrio en plata al mes (aproximado) | B39: =B35*C31 -> 800000
A40: Lo que vendo hoy al día (unidades) | B40: =B31 -> 40
A41: ¿Cómo voy? | B41: =IF(B31=0,"Escribe tus unidades",IF(B31>=B38,"Por encima del punto de equilibrio","Por debajo del punto de equilibrio")) -> Por encima del punto de equilibrio
