Workbook

Sheet Cómo usar
B1: Tarea guiada: flujo de caja, PyG, cascada de utilidades y política de bolsillos (A9)
B2: Ruta HACER · Semanas 4 y 6 · Centro de Innovación Comunitario · Red de Mujeres del Caribe
B4: Para qué sirve
B5: Para saber si tu negocio ganó o perdió en dos semanas, cuánto te queda de verdad y cómo repartirlo en tus bolsillos de emergencia, crecimiento e innovación. Se revisa en la semana 6. Es un apoyo opcional: también se puede hacer en papel con la hoja impresa A9.
B7: Cómo se usa
B8: 1. Hoja «Flujo de caja»: escribe el saldo inicial de la caja del negocio y la fecha del primer día. Cada día, anota en las celdas amarillas lo que entró y lo que salió (con ayuda de tu registro diario). El saldo se calcula solo.
B9: 2. Hoja «PyG»: se llena sola con los totales del flujo. Solo escribe, si las hubo, las ventas fiadas de estas dos semanas que todavía no te han pagado.
B10: 3. Hoja «Cascada»: escribe cuánto de tus cuotas de préstamos fue interés y si pagaste impuestos del negocio. La hoja baja de la utilidad operacional a la neta y a la líquida, y revisa que cuadre con tu caja.
B11: 4. Hoja «Política de bolsillos»: escribe qué porcentaje de tu utilidad líquida va a cada bolsillo (deben sumar 100 %). Luego pasa esos valores a los bolsillos de tu billetera digital, a sobres o a alcancías.
B13: Importante
B14: Las filas con fondo crema y letra gris son un EJEMPLO (Marta, jugos naturales; dos semanas de clases; caso ilustrativo). Bórralas o escribe encima antes de usar la hoja con tus datos.
B15: «Me pagué» es el pago de tu trabajo (lo que calculaste en A8). Lo que saques para la casa además de eso va en «Otros retiros para la casa».
... B19: Celda amarilla = la llenas tú. Celda blanca = se calcula sola, no la borres.

Sheet Flujo de caja
A1: Flujo de caja de dos semanas
A2: Saldo inicial de la caja del negocio: | D2: 50000
A3: Fecha del primer día: | D3: 46300
A5: Fecha | B5: Día | C5: Ventas de contado | D5: Cobros de fiados de antes | E5: Préstamos o aportes recibidos | F5: Materia prima | G5: Costos indirectos | H5: Gastos (arriendo, bodegaje, recargas…) | I5: Cuotas de préstamos | J5: Me pagué (mi trabajo) | K5: Otros retiros para la casa | L5: Nota | M5: Total entró | N5: Total salió | O5: Saldo de la caja
A6: =$D$3+0 -> 46300 | B6: =CHOOSE(WEEKDAY(A6,2),"Lunes","Martes","Miércoles","Jueves","Viernes","Sábado","Domingo") -> Lunes | C6: 96000 | F6: 49200 | G6: 6800 | H6: 40000 | J6: 18400 | L6: Bodegaje del carrito (quincena) | M6: =SUM(C6:E6) -> 96000 | N6: =SUM(F6:K6) -> 114400 | O6: =$D$2+M6-N6 -> 31600
A7: =$D$3+1 -> 46301 | B7: =CHOOSE(WEEKDAY(A7,2),"Lunes","Martes","Miércoles","Jueves","Viernes","Sábado","Domingo") -> Martes | C7: 96000 | F7: 49200 | G7: 6800 | J7: 18400 | M7: =SUM(C7:E7) -> 96000 | N7: =SUM(F7:K7) -> 74400 | O7: =O6+M7-N7 -> 53200
A8: =$D$3+2 -> 46302 | B8: =CHOOSE(WEEKDAY(A8,2),"Lunes","Martes","Miércoles","Jueves","Viernes","Sábado","Domingo") -> Miércoles | C8: 96000 | F8: 49200 | G8: 6800 | H8: 15000 | J8: 18400 | L8: Recarga del celular | M8: =SUM(C8:E8) -> 96000 | N8: =SUM(F8:K8) -> 89400 | O8: =O7+M8-N8 -> 59800
A9: =$D$3+3 -> 46303 | B9: =CHOOSE(WEEKDAY(A9,2),"Lunes","Martes","Miércoles","Jueves","Viernes","Sábado","Domingo") -> Jueves | C9: 96000 | F9: 49200 | G9: 6800 | J9: 18400 | M9: =SUM(C9:E9) -> 96000 | N9: =SUM(F9:K9) -> 74400 | O9: =O8+M9-N9 -> 81400
A10: =$D$3+4 -> 46304 | B10: =CHOOSE(WEEKDAY(A10,2),"Lunes","Martes","Miércoles","Jueves","Viernes","Sábado","Domingo") -> Viernes | C10: 96000 | F10: 49200 | G10: 6800 | H10: 20000 | J10: 18400 | L10: Mantenimiento de licuadora y carrito | M10: =SUM(C10:E10) -> 96000 | N10: =SUM(F10:K10) -> 94400 | O10: =O9+M10-N10 -> 83000
A11: =$D$3+5 -> 46305 | B11: =CHOOSE(WEEKDAY(A11,2),"Lunes","Martes","Miércoles","Jueves","Viernes","Sábado","Domingo") -> Sábado | M11: =SUM(C11:E11) -> 0 | N11: =SUM(F11:K11) -> 0 | O11: =O10+M11-N11 -> 83000
A12: =$D$3+6 -> 46306 | B12: =CHOOSE(WEEKDAY(A12,2),"Lunes","Martes","Miércoles","Jueves","Viernes","Sábado","Domingo") -> Domingo | M12: =SUM(C12:E12) -> 0 | N12: =SUM(F12:K12) -> 0 | O12: =O11+M12-N12 -> 83000
A13: =$D$3+7 -> 46307 | B13: =CHOOSE(WEEKDAY(A13,2),"Lunes","Martes","Miércoles","Jueves","Viernes","Sábado","Domingo") -> Lunes | C13: 96000 | F13: 49200 | G13: 6800 | H13: 15000 | J13: 18400 | L13: Aporte por el uso del espacio | M13: =SUM(C13:E13) -> 96000 | N13: =SUM(F13:K13) -> 89400 | O13: =O12+M13-N13 -> 89600
A14: =$D$3+8 -> 46308 | B14: =CHOOSE(WEEKDAY(A14,2),"Lunes","Martes","Miércoles","Jueves","Viernes","Sábado","Domingo") -> Martes | C14: 96000 | F14: 49200 | G14: 6800 | J14: 18400 | M14: =SUM(C14:E14) -> 96000 | N14: =SUM(F14:K14) -> 74400 | O14: =O13+M14-N14 -> 111200
A15: =$D$3+9 -> 46309 | B15: =CHOOSE(WEEKDAY(A15,2),"Lunes","Martes","Miércoles","Jueves","Viernes","Sábado","Domingo") -> Miércoles | C15: 96000 | F15: 49200 | G15: 6800 | J15: 18400 | K15: 26000 | L15: Útiles escolares | M15: =SUM(C15:E15) -> 96000 | N15: =SUM(F15:K15) -> 100400 | O15: =O14+M15-N15 -> 106800
A16: =$D$3+10 -> 46310 | B16: =CHOOSE(WEEKDAY(A16,2),"Lunes","Martes","Miércoles","Jueves","Viernes","Sábado","Domingo") -> Jueves | C16: 96000 | F16: 49200 | G16: 6800 | J16: 18400 | M16: =SUM(C16:E16) -> 96000 | N16: =SUM(F16:K16) -> 74400 | O16: =O15+M16-N16 -> 128400
A17: =$D$3+11 -> 46311 | B17: =CHOOSE(WEEKDAY(A17,2),"Lunes","Martes","Miércoles","Jueves","Viernes","Sábado","Domingo") -> Viernes | C17: 96000 | F17: 49200 | G17: 6800 | J17: 18400 | M17: =SUM(C17:E17) -> 96000 | N17: =SUM(F17:K17) -> 74400 | O17: =O16+M17-N17 -> 150000
A18: =$D$3+12 -> 46312 | B18: =CHOOSE(WEEKDAY(A18,2),"Lunes","Martes","Miércoles","Jueves","Viernes","Sábado","Domingo") -> Sábado | M18: =SUM(C18:E18) -> 0 | N18: =SUM(F18:K18) -> 0 | O18: =O17+M18-N18 -> 150000
A19: =$D$3+13 -> 46313 | B19: =CHOOSE(WEEKDAY(A19,2),"Lunes","Martes","Miércoles","Jueves","Viernes","Sábado","Domingo") -> Domingo | M19: =SUM(C19:E19) -> 0 | N19: =SUM(F19:K19) -> 0 | O19: =O18+M19-N19 -> 150000
A20: Totales | C20: =SUM(C6:C19) -> 960000 | D20: =SUM(D6:D19) -> 0 | E20: =SUM(E6:E19) -> 0 | F20: =SUM(F6:F19) -> 492000 | G20: =SUM(G6:G19) -> 68000 | H20: =SUM(H6:H19) -> 90000 | I20: =SUM(I6:I19) -> 0 | J20: =SUM(J6:J19) -> 184000 | K20: =SUM(K6:K19) -> 26000 | M20: =SUM(M6:M19) -> 960000 | N20: =SUM(N6:N19) -> 860000 | O20: =O19 -> 150000
A22: Saldo = saldo del día anterior + total entró − total salió. Los fines de semana, si no vendes, deja la fila en blanco.
A23: Las filas crema son el ejemplo de Marta: bórralas o escribe encima.

Sheet PyG
A1: Estado de resultados (PyG) sencillo · dos semanas
A3: Concepto | B3: Valor | C3: De dónde sale
A4: Ventas de contado | B4: ='Flujo de caja'!C20 -> 960000 | C4: Total de «Ventas de contado» del flujo
A5: Ventas fiadas de estas semanas que todavía no te pagan | B5: 0 | C5: Escríbelas tú (celda amarilla)
A6: Ventas de las dos semanas | B6: =B4+B5 -> 960000
A7: − Materia prima | B7: ='Flujo de caja'!F20 -> 492000 | C7: Flujo de caja
A8: − Mano de obra (lo que me pagué) | B8: ='Flujo de caja'!J20 -> 184000 | C8: Flujo de caja
A9: − Costos indirectos | B9: ='Flujo de caja'!G20 -> 68000 | C9: Flujo de caja
A10: = Margen de contribución | B10: =B6-B7-B8-B9 -> 216000 | C10: Ventas − costos de lo vendido
A11: − Gastos | B11: ='Flujo de caja'!H20 -> 90000 | C11: Flujo de caja (sin cuotas de préstamos)
A12: = Utilidad operacional | B12: =B10-B11 -> 126000 | C12: Margen − gastos
A14: ¿El negocio ganó en estas dos semanas? | B14: =IF(B12>0,"Sí: ganó",IF(B12=0,"Quedó en cero","No: perdió")) -> Sí: ganó

Sheet Cascada
A1: Cascada de utilidades
A3: Escalón | B3: Valor | C3: De dónde sale
A4: Utilidad operacional | B4: =PyG!B12 -> 126000 | C4: Hoja PyG
A5: − Intereses de préstamos del negocio | B5: 0 | C5: Escríbelo tú: de tus cuotas, cuánto fue interés
A6: − Impuestos del negocio | B6: 0 | C6: Escríbelo tú, si pagaste en el periodo
A7: = Utilidad neta | B7: =B4-B5-B6 -> 126000 | C7: Operacional − intereses − impuestos
A8: − Abonos a deudas (capital) | B8: ='Flujo de caja'!I20-B5 -> 0 | C8: Cuotas pagadas − intereses
A9: − Otros retiros para la casa | B9: ='Flujo de caja'!K20 -> 26000 | C9: Lo que sacaste además de tu pago
A10: − Ventas fiadas que todavía no te pagan | B10: =PyG!B5 -> 0 | C10: Hoja PyG
A11: + Fiados de antes que cobraste | B11: ='Flujo de caja'!D20 -> 0 | C11: Flujo de caja
A12: = Utilidad líquida | B12: =B7-B8-B9-B10+B11 -> 100000 | C12: Lo que de verdad queda para ahorrar, reinvertir o repartir
A14: Revisión con la caja
A15: Lo que creció la caja (saldo final − saldo inicial) | B15: ='Flujo de caja'!O20-'Flujo de caja'!D2 -> 100000
A16: − Préstamos o aportes recibidos (no son utilidad) | B16: ='Flujo de caja'!E20 -> 0
A17: = Debe ser igual a la utilidad líquida | B17: =B15-B16 -> 100000
A18: ¿Cuadra? | B18: =IF(ABS(B17-B12)<1,"✔ Cuadra con la caja","Revisa: falta anotar algo") -> ✔ Cuadra con la caja

Sheet Política de bolsillos
A1: Mi política de bolsillos
A3: Utilidad líquida para repartir | C3: =MAX(Cascada!B12,0) -> 100000
A5: Bolsillo | B5: Para qué es | C5: % (tú decides) | D5: Valor | E5: Dónde lo guardo
A6: Emergencia | B6: Imprevistos: una enfermedad, un equipo dañado, semanas sin ventas. | C6: 0.5 | D6: =$C$3*C6 -> 50000 | E6: Bolsillo «Emergencia» de la billetera digital
A7: Crecimiento | B7: Invertir en el negocio: equipos, más mercancía, un producto nuevo. | C7: 0.3 | D7: =$C$3*C7 -> 30000 | E7: Bolsillo «Crecimiento»
A8: Innovación | B8: Probar cosas nuevas: muestras, empaques, un curso. | C8: 0.2 | D8: =$C$3*C8 -> 20000 | E8: Bolsillo «Innovación»
A9: Total | C9: =SUM(C6:C8) -> 1 | D9: =SUM(D6:D8) -> 100000
A10: ¿Suma 100 %? | C10: =IF(ROUND(C9,4)=1,"✔ Suma 100 %","Revisa: los porcentajes deben sumar 100 %") -> ✔ Suma 100 %
A12: Meta del fondo de emergencia
A13: Gastos que pagas en un mes (buena meta para el fondo) | C13: 180000
A14: ¿En cuántas quincenas llenas el fondo, al ritmo de hoy? | C14: =IF(D6<=0,"-",ROUNDUP(C13/D6,0)) -> 4
A16: Crea tres bolsillos en tu billetera digital (o usa tres sobres o alcancías) y pasa a cada uno su valor cada vez que calcules tu utilidad líquida. El bolsillo de emergencia no se toca para gastos de todos los días.
